diff_timer/__init__.py
diff_timer/controller.py
diff_timer/test.py
diff_timer/heapTimer/__init__.py
diff_timer/heapTimer/heapTimer.py
diff_timer/timer/__init__.py
diff_timer/timer/timer.py
diff_timer/wheelTimer/__init__.py
diff_timer/wheelTimer/defines.py
diff_timer/wheelTimer/taskList.py
diff_timer/wheelTimer/wheelTimer.py
diff_timer-0.1.4.dist-info/LICENSE
diff_timer-0.1.4.dist-info/METADATA
diff_timer-0.1.4.dist-info/WHEEL
diff_timer-0.1.4.dist-info/top_level.txt
diff_timer-0.1.4.dist-info/RECORD
