Metadata-Version: 2.1
Name: diff-timer
Version: 0.1.4
Summary: Several timers base on Python
Home-page: https://github.com/HebeTien0330/diff_timer
Author: Clarify
Author-email: 527094604@qq.com
License: MIT
Classifier: License :: OSI Approved :: MIT License
Classifier: Programming Language :: Python
Classifier: Programming Language :: Python :: 3
Classifier: Programming Language :: Python :: 3.6
Classifier: Programming Language :: Python :: Implementation :: CPython
Classifier: Programming Language :: Python :: Implementation :: PyPy
Requires-Python: >=3.6.0
License-File: LICENSE
